MANIFEST.in
MIT-LICENSE.txt
README.md
setup.py
django_chile_payments.egg-info/PKG-INFO
django_chile_payments.egg-info/SOURCES.txt
django_chile_payments.egg-info/dependency_links.txt
django_chile_payments.egg-info/requires.txt
django_chile_payments.egg-info/top_level.txt
docs/index.md
docs/webpay.md
docs/workflow.md
getpaid/__init__.py
getpaid/abstract_mixin.py
getpaid/admin.py
getpaid/forms.py
getpaid/middleware.py
getpaid/models.py
getpaid/signals.py
getpaid/urls.py
getpaid/utils.py
getpaid/views.py
getpaid/backends/__init__.py
getpaid/backends/dummy/__init__.py
getpaid/backends/dummy/forms.py
getpaid/backends/dummy/models.py
getpaid/backends/dummy/urls.py
getpaid/backends/dummy/views.py
getpaid/backends/webpay/__init__.py
getpaid/backends/webpay/admin.py
getpaid/backends/webpay/models.py
getpaid/backends/webpay/tests.py
getpaid/backends/webpay/urls.py
getpaid/backends/webpay/views.py
getpaid/backends/webpaypure/__init__.py
getpaid/backends/webpaypure/admin.py
getpaid/backends/webpaypure/models.py
getpaid/backends/webpaypure/tests.py
getpaid/backends/webpaypure/urls.py
getpaid/backends/webpaypure/views.py